{"nodes": [{"id": "ninety_view_root_guidedtourview_swift", "label": "GuidedTourView.swift", "file_type": "code", "source_file": "Ninety/View/Root/GuidedTourView.swift", "source_location": "L1"}, {"id": "guidedtourview_tourframestore", "label": "TourFrameStore", "file_type": "code", "source_file": "Ninety/View/Root/GuidedTourView.swift", "source_location": "L13"}, {"id": "observableobject", "label": "ObservableObject", "file_type": "code", "source_file": "", "source_location": ""}, {"id": "guidedtourview_tourstep", "label": "TourStep", "file_type": "code", "source_file": "Ninety/View/Root/GuidedTourView.swift", "source_location": "L21"}, {"id": "int", "label": "Int", "file_type": "code", "source_file": "", "source_location": ""}, {"id": "caseiterable", "label": "CaseIterable", "file_type": "code", "source_file": "", "source_location": ""}, {"id": "guidedtourview_tourstep_welcome", "label": "welcome", "file_type": "code", "source_file": "Ninety/View/Root/GuidedTourView.swift", "source_location": "L22"}, {"id": "guidedtourview_tourstep_timepicker", "label": "timePicker", "file_type": "code", "source_file": "Ninety/View/Root/GuidedTourView.swift", "source_location": "L22"}, {"id": "guidedtourview_tourstep_dayselector", "label": "daySelector", "file_type": "code", "source_file": "Ninety/View/Root/GuidedTourView.swift", "source_location": "L22"}, {"id": "guidedtourview_tourstep_alarmtoggle", "label": "alarmToggle", "file_type": "code", "source_file": "Ninety/View/Root/GuidedTourView.swift", "source_location": "L22"}, {"id": "guidedtourview_tourstep_privacy", "label": "privacy", "file_type": "code", "source_file": "Ninety/View/Root/GuidedTourView.swift", "source_location": "L22"}, {"id": "guidedtourview_tourstep_ready", "label": "ready", "file_type": "code", "source_file": "Ninety/View/Root/GuidedTourView.swift", "source_location": "L22"}, {"id": "guidedtourview_guidedtourview", "label": "GuidedTourView", "file_type": "code", "source_file": "Ninety/View/Root/GuidedTourView.swift", "source_location": "L70"}, {"id": "view", "label": "View", "file_type": "code", "source_file": "", "source_location": ""}, {"id": "guidedtourview_guidedtourview_init", "label": ".init()", "file_type": "code", "source_file": "Ninety/View/Root/GuidedTourView.swift", "source_location": "L92"}, {"id": "guidedtourview_guidedtourview_group", "label": ".group()", "file_type": "code", "source_file": "Ninety/View/Root/GuidedTourView.swift", "source_location": "L133"}, {"id": "guidedtourview_guidedtourview_fullcard", "label": ".fullCard()", "file_type": "code", "source_file": "Ninety/View/Root/GuidedTourView.swift", "source_location": "L144"}, {"id": "guidedtourview_guidedtourview_spotcard", "label": ".spotCard()", "file_type": "code", "source_file": "Ninety/View/Root/GuidedTourView.swift", "source_location": "L185"}, {"id": "guidedtourview_guidedtourview_go", "label": ".go()", "file_type": "code", "source_file": "Ninety/View/Root/GuidedTourView.swift", "source_location": "L307"}, {"id": "guidedtourview_guidedtourview_close", "label": ".close()", "file_type": "code", "source_file": "Ninety/View/Root/GuidedTourView.swift", "source_location": "L318"}, {"id": "guidedtourview_spotlightshape", "label": "SpotlightShape", "file_type": "code", "source_file": "Ninety/View/Root/GuidedTourView.swift", "source_location": "L327"}, {"id": "shape", "label": "Shape", "file_type": "code", "source_file": "", "source_location": ""}, {"id": "guidedtourview_spotlightshape_path", "label": ".path()", "file_type": "code", "source_file": "Ninety/View/Root/GuidedTourView.swift", "source_location": "L330"}, {"id": "guidedtourview_tourtargetrole", "label": "TourTargetRole", "file_type": "code", "source_file": "Ninety/View/Root/GuidedTourView.swift", "source_location": "L340"}, {"id": "guidedtourview_tourtargetrole_clockpill", "label": "clockPill", "file_type": "code", "source_file": "Ninety/View/Root/GuidedTourView.swift", "source_location": "L340"}, {"id": "guidedtourview_tourtargetrole_dayselector", "label": "daySelector", "file_type": "code", "source_file": "Ninety/View/Root/GuidedTourView.swift", "source_location": "L340"}, {"id": "guidedtourview_tourtargetrole_alarmbutton", "label": "alarmButton", "file_type": "code", "source_file": "Ninety/View/Root/GuidedTourView.swift", "source_location": "L340"}, {"id": "guidedtourview_tourtargetmodifier", "label": "TourTargetModifier", "file_type": "code", "source_file": "Ninety/View/Root/GuidedTourView.swift", "source_location": "L342"}, {"id": "viewmodifier", "label": "ViewModifier", "file_type": "code", "source_file": "", "source_location": ""}, {"id": "guidedtourview_tourtargetmodifier_body", "label": ".body()", "file_type": "code", "source_file": "Ninety/View/Root/GuidedTourView.swift", "source_location": "L346"}, {"id": "guidedtourview_view", "label": "View", "file_type": "code", "source_file": "Ninety/View/Root/GuidedTourView.swift", "source_location": "L360"}, {"id": "guidedtourview_view_tourtarget", "label": ".tourTarget()", "file_type": "code", "source_file": "Ninety/View/Root/GuidedTourView.swift", "source_location": "L361"}, {"id": "guidedtourview_comparable", "label": "Comparable", "file_type": "code", "source_file": "Ninety/View/Root/GuidedTourView.swift", "source_location": "L368"}, {"id": "guidedtourview_comparable_clamped", "label": ".clamped()", "file_type": "code", "source_file": "Ninety/View/Root/GuidedTourView.swift", "source_location": "L369"}, {"id": "guidedtourview_guidedtourpreviewhost", "label": "GuidedTourPreviewHost", "file_type": "code", "source_file": "Ninety/View/Root/GuidedTourView.swift", "source_location": "L372"}], "edges": [{"source": "ninety_view_root_guidedtourview_swift", "target": "swiftui", "relation": "imports", "confidence": "EXTRACTED", "source_file": "Ninety/View/Root/GuidedTourView.swift", "source_location": "L9", "weight": 1.0}, {"source": "ninety_view_root_guidedtourview_swift", "target": "guidedtourview_tourframestore", "relation": "contains", "confidence": "EXTRACTED", "source_file": "Ninety/View/Root/GuidedTourView.swift", "source_location": "L13", "weight": 1.0}, {"source": "guidedtourview_tourframestore", "target": "observableobject", "relation": "inherits", "confidence": "EXTRACTED", "source_file": "Ninety/View/Root/GuidedTourView.swift", "source_location": "L13", "weight": 1.0}, {"source": "ninety_view_root_guidedtourview_swift", "target": "guidedtourview_tourstep", "relation": "contains", "confidence": "EXTRACTED", "source_file": "Ninety/View/Root/GuidedTourView.swift", "source_location": "L21", "weight": 1.0}, {"source": "guidedtourview_tourstep", "target": "int", "relation": "inherits", "confidence": "EXTRACTED", "source_file": "Ninety/View/Root/GuidedTourView.swift", "source_location": "L21", "weight": 1.0}, {"source": "guidedtourview_tourstep", "target": "caseiterable", "relation": "inherits", "confidence": "EXTRACTED", "source_file": "Ninety/View/Root/GuidedTourView.swift", "source_location": "L21", "weight": 1.0}, {"source": "guidedtourview_tourstep", "target": "guidedtourview_tourstep_welcome", "relation": "case_of", "confidence": "EXTRACTED", "source_file": "Ninety/View/Root/GuidedTourView.swift", "source_location": "L22", "weight": 1.0}, {"source": "guidedtourview_tourstep", "target": "guidedtourview_tourstep_timepicker", "relation": "case_of", "confidence": "EXTRACTED", "source_file": "Ninety/View/Root/GuidedTourView.swift", "source_location": "L22", "weight": 1.0}, {"source": "guidedtourview_tourstep", "target": "guidedtourview_tourstep_dayselector", "relation": "case_of", "confidence": "EXTRACTED", "source_file": "Ninety/View/Root/GuidedTourView.swift", "source_location": "L22", "weight": 1.0}, {"source": "guidedtourview_tourstep", "target": "guidedtourview_tourstep_alarmtoggle", "relation": "case_of", "confidence": "EXTRACTED", "source_file": "Ninety/View/Root/GuidedTourView.swift", "source_location": "L22", "weight": 1.0}, {"source": "guidedtourview_tourstep", "target": "guidedtourview_tourstep_privacy", "relation": "case_of", "confidence": "EXTRACTED", "source_file": "Ninety/View/Root/GuidedTourView.swift", "source_location": "L22", "weight": 1.0}, {"source": "guidedtourview_tourstep", "target": "guidedtourview_tourstep_ready", "relation": "case_of", "confidence": "EXTRACTED", "source_file": "Ninety/View/Root/GuidedTourView.swift", "source_location": "L22", "weight": 1.0}, {"source": "ninety_view_root_guidedtourview_swift", "target": "guidedtourview_guidedtourview", "relation": "contains", "confidence": "EXTRACTED", "source_file": "Ninety/View/Root/GuidedTourView.swift", "source_location": "L70", "weight": 1.0}, {"source": "guidedtourview_guidedtourview", "target": "view", "relation": "inherits", "confidence": "EXTRACTED", "source_file": "Ninety/View/Root/GuidedTourView.swift", "source_location": "L70", "weight": 1.0}, {"source": "guidedtourview_guidedtourview", "target": "guidedtourview_guidedtourview_init", "relation": "method", "confidence": "EXTRACTED", "source_file": "Ninety/View/Root/GuidedTourView.swift", "source_location": "L92", "weight": 1.0}, {"source": "guidedtourview_guidedtourview", "target": "guidedtourview_guidedtourview_init", "relation": "method", "confidence": "EXTRACTED", "source_file": "Ninety/View/Root/GuidedTourView.swift", "source_location": "L96", "weight": 1.0}, {"source": "guidedtourview_guidedtourview", "target": "guidedtourview_guidedtourview_group", "relation": "method", "confidence": "EXTRACTED", "source_file": "Ninety/View/Root/GuidedTourView.swift", "source_location": "L133", "weight": 1.0}, {"source": "guidedtourview_guidedtourview", "target": "guidedtourview_guidedtourview_fullcard", "relation": "method", "confidence": "EXTRACTED", "source_file": "Ninety/View/Root/GuidedTourView.swift", "source_location": "L144", "weight": 1.0}, {"source": "guidedtourview_guidedtourview", "target": "guidedtourview_guidedtourview_spotcard", "relation": "method", "confidence": "EXTRACTED", "source_file": "Ninety/View/Root/GuidedTourView.swift", "source_location": "L185", "weight": 1.0}, {"source": "guidedtourview_guidedtourview", "target": "guidedtourview_guidedtourview_go", "relation": "method", "confidence": "EXTRACTED", "source_file": "Ninety/View/Root/GuidedTourView.swift", "source_location": "L307", "weight": 1.0}, {"source": "guidedtourview_guidedtourview", "target": "guidedtourview_guidedtourview_close", "relation": "method", "confidence": "EXTRACTED", "source_file": "Ninety/View/Root/GuidedTourView.swift", "source_location": "L318", "weight": 1.0}, {"source": "ninety_view_root_guidedtourview_swift", "target": "guidedtourview_spotlightshape", "relation": "contains", "confidence": "EXTRACTED", "source_file": "Ninety/View/Root/GuidedTourView.swift", "source_location": "L327", "weight": 1.0}, {"source": "guidedtourview_spotlightshape", "target": "shape", "relation": "inherits", "confidence": "EXTRACTED", "source_file": "Ninety/View/Root/GuidedTourView.swift", "source_location": "L327", "weight": 1.0}, {"source": "guidedtourview_spotlightshape", "target": "guidedtourview_spotlightshape_path", "relation": "method", "confidence": "EXTRACTED", "source_file": "Ninety/View/Root/GuidedTourView.swift", "source_location": "L330", "weight": 1.0}, {"source": "ninety_view_root_guidedtourview_swift", "target": "guidedtourview_tourtargetrole", "relation": "contains", "confidence": "EXTRACTED", "source_file": "Ninety/View/Root/GuidedTourView.swift", "source_location": "L340", "weight": 1.0}, {"source": "guidedtourview_tourtargetrole", "target": "guidedtourview_tourtargetrole_clockpill", "relation": "case_of", "confidence": "EXTRACTED", "source_file": "Ninety/View/Root/GuidedTourView.swift", "source_location": "L340", "weight": 1.0}, {"source": "guidedtourview_tourtargetrole", "target": "guidedtourview_tourtargetrole_dayselector", "relation": "case_of", "confidence": "EXTRACTED", "source_file": "Ninety/View/Root/GuidedTourView.swift", "source_location": "L340", "weight": 1.0}, {"source": "guidedtourview_tourtargetrole", "target": "guidedtourview_tourtargetrole_alarmbutton", "relation": "case_of", "confidence": "EXTRACTED", "source_file": "Ninety/View/Root/GuidedTourView.swift", "source_location": "L340", "weight": 1.0}, {"source": "ninety_view_root_guidedtourview_swift", "target": "guidedtourview_tourtargetmodifier", "relation": "contains", "confidence": "EXTRACTED", "source_file": "Ninety/View/Root/GuidedTourView.swift", "source_location": "L342", "weight": 1.0}, {"source": "guidedtourview_tourtargetmodifier", "target": "viewmodifier", "relation": "inherits", "confidence": "EXTRACTED", "source_file": "Ninety/View/Root/GuidedTourView.swift", "source_location": "L342", "weight": 1.0}, {"source": "guidedtourview_tourtargetmodifier", "target": "guidedtourview_tourtargetmodifier_body", "relation": "method", "confidence": "EXTRACTED", "source_file": "Ninety/View/Root/GuidedTourView.swift", "source_location": "L346", "weight": 1.0}, {"source": "ninety_view_root_guidedtourview_swift", "target": "guidedtourview_view", "relation": "contains", "confidence": "EXTRACTED", "source_file": "Ninety/View/Root/GuidedTourView.swift", "source_location": "L360", "weight": 1.0}, {"source": "guidedtourview_view", "target": "guidedtourview_view_tourtarget", "relation": "method", "confidence": "EXTRACTED", "source_file": "Ninety/View/Root/GuidedTourView.swift", "source_location": "L361", "weight": 1.0}, {"source": "ninety_view_root_guidedtourview_swift", "target": "guidedtourview_comparable", "relation": "contains", "confidence": "EXTRACTED", "source_file": "Ninety/View/Root/GuidedTourView.swift", "source_location": "L368", "weight": 1.0}, {"source": "guidedtourview_comparable", "target": "guidedtourview_comparable_clamped", "relation": "method", "confidence": "EXTRACTED", "source_file": "Ninety/View/Root/GuidedTourView.swift", "source_location": "L369", "weight": 1.0}, {"source": "ninety_view_root_guidedtourview_swift", "target": "guidedtourview_guidedtourpreviewhost", "relation": "contains", "confidence": "EXTRACTED", "source_file": "Ninety/View/Root/GuidedTourView.swift", "source_location": "L372", "weight": 1.0}, {"source": "guidedtourview_guidedtourpreviewhost", "target": "guidedtourview_view", "relation": "inherits", "confidence": "EXTRACTED", "source_file": "Ninety/View/Root/GuidedTourView.swift", "source_location": "L372", "weight": 1.0}, {"source": "guidedtourview_guidedtourview_group", "target": "guidedtourview_guidedtourview_fullcard", "relation": "calls", "confidence": "EXTRACTED", "source_file": "Ninety/View/Root/GuidedTourView.swift", "source_location": "L136", "weight": 1.0}, {"source": "guidedtourview_guidedtourview_group", "target": "guidedtourview_guidedtourview_spotcard", "relation": "calls", "confidence": "EXTRACTED", "source_file": "Ninety/View/Root/GuidedTourView.swift", "source_location": "L138", "weight": 1.0}, {"source": "guidedtourview_guidedtourview_spotcard", "target": "guidedtourview_comparable_clamped", "relation": "calls", "confidence": "EXTRACTED", "source_file": "Ninety/View/Root/GuidedTourView.swift", "source_location": "L200", "weight": 1.0}, {"source": "guidedtourview_guidedtourview_spotcard", "target": "guidedtourview_spotlightshape", "relation": "calls", "confidence": "EXTRACTED", "source_file": "Ninety/View/Root/GuidedTourView.swift", "source_location": "L204", "weight": 1.0}, {"source": "guidedtourview_guidedtourview_go", "target": "guidedtourview_tourstep", "relation": "calls", "confidence": "EXTRACTED", "source_file": "Ninety/View/Root/GuidedTourView.swift", "source_location": "L310", "weight": 1.0}, {"source": "guidedtourview_view_tourtarget", "target": "guidedtourview_tourtargetmodifier", "relation": "calls", "confidence": "EXTRACTED", "source_file": "Ninety/View/Root/GuidedTourView.swift", "source_location": "L362", "weight": 1.0}], "raw_calls": [{"caller_nid": "guidedtourview_guidedtourview_init", "callee": "State", "source_file": "Ninety/View/Root/GuidedTourView.swift", "source_location": "L98"}, {"caller_nid": "guidedtourview_guidedtourview_fullcard", "callee": "frame", "source_file": "Ninety/View/Root/GuidedTourView.swift", "source_location": "L145"}, {"caller_nid": "guidedtourview_guidedtourview_fullcard", "callee": "VStack", "source_file": "Ninety/View/Root/GuidedTourView.swift", "source_location": "L145"}, {"caller_nid": "guidedtourview_guidedtourview_fullcard", "callee": "Spacer", "source_file": "Ninety/View/Root/GuidedTourView.swift", "source_location": "L146"}, {"caller_nid": "guidedtourview_guidedtourview_fullcard", "callee": "scaleEffect", "source_file": "Ninety/View/Root/GuidedTourView.swift", "source_location": "L148"}, {"caller_nid": "guidedtourview_guidedtourview_fullcard", "callee": "glassEffect", "source_file": "Ninety/View/Root/GuidedTourView.swift", "source_location": "L148"}, {"caller_nid": "guidedtourview_guidedtourview_fullcard", "callee": "frame", "source_file": "Ninety/View/Root/GuidedTourView.swift", "source_location": "L148"}, {"caller_nid": "guidedtourview_guidedtourview_fullcard", "callee": "padding", "source_file": "Ninety/View/Root/GuidedTourView.swift", "source_location": "L148"}, {"caller_nid": "guidedtourview_guidedtourview_fullcard", "callee": "padding", "source_file": "Ninety/View/Root/GuidedTourView.swift", "source_location": "L148"}, {"caller_nid": "guidedtourview_guidedtourview_fullcard", "callee": "VStack", "source_file": "Ninety/View/Root/GuidedTourView.swift", "source_location": "L148"}, {"caller_nid": "guidedtourview_guidedtourview_fullcard", "callee": "rotationEffect", "source_file": "Ninety/View/Root/GuidedTourView.swift", "source_location": "L150"}, {"caller_nid": "guidedtourview_guidedtourview_fullcard", "callee": "background", "source_file": "Ninety/View/Root/GuidedTourView.swift", "source_location": "L150"}, {"caller_nid": "guidedtourview_guidedtourview_fullcard", "callee": "padding", "source_file": "Ninety/View/Root/GuidedTourView.swift", "source_location": "L150"}, {"caller_nid": "guidedtourview_guidedtourview_fullcard", "callee": "symbolRenderingMode", "source_file": "Ninety/View/Root/GuidedTourView.swift", "source_location": "L150"}, {"caller_nid": "guidedtourview_guidedtourview_fullcard", "callee": "foregroundStyle", "source_file": "Ninety/View/Root/GuidedTourView.swift", "source_location": "L150"}, {"caller_nid": "guidedtourview_guidedtourview_fullcard", "callee": "font", "source_file": "Ninety/View/Root/GuidedTourView.swift", "source_location": "L150"}, {"caller_nid": "guidedtourview_guidedtourview_fullcard", "callee": "Image", "source_file": "Ninety/View/Root/GuidedTourView.swift", "source_location": "L150"}, {"caller_nid": "guidedtourview_guidedtourview_fullcard", "callee": "fill", "source_file": "Ninety/View/Root/GuidedTourView.swift", "source_location": "L155"}, {"caller_nid": "guidedtourview_guidedtourview_fullcard", "callee": "Circle", "source_file": "Ninety/View/Root/GuidedTourView.swift", "source_location": "L155"}, {"caller_nid": "guidedtourview_guidedtourview_fullcard", "callee": "opacity", "source_file": "Ninety/View/Root/GuidedTourView.swift", "source_location": "L155"}, {"caller_nid": "guidedtourview_guidedtourview_fullcard", "callee": "multilineTextAlignment", "source_file": "Ninety/View/Root/GuidedTourView.swift", "source_location": "L158"}, {"caller_nid": "guidedtourview_guidedtourview_fullcard", "callee": "font", "source_file": "Ninety/View/Root/GuidedTourView.swift", "source_location": "L158"}, {"caller_nid": "guidedtourview_guidedtourview_fullcard", "callee": "Text", "source_file": "Ninety/View/Root/GuidedTourView.swift", "source_location": "L158"}, {"caller_nid": "guidedtourview_guidedtourview_fullcard", "callee": "localized", "source_file": "Ninety/View/Root/GuidedTourView.swift", "source_location": "L158"}, {"caller_nid": "guidedtourview_guidedtourview_fullcard", "callee": "padding", "source_file": "Ninety/View/Root/GuidedTourView.swift", "source_location": "L162"}, {"caller_nid": "guidedtourview_guidedtourview_fullcard", "callee": "lineLimit", "source_file": "Ninety/View/Root/GuidedTourView.swift", "source_location": "L162"}, {"caller_nid": "guidedtourview_guidedtourview_fullcard", "callee": "lineSpacing", "source_file": "Ninety/View/Root/GuidedTourView.swift", "source_location": "L162"}, {"caller_nid": "guidedtourview_guidedtourview_fullcard", "callee": "multilineTextAlignment", "source_file": "Ninety/View/Root/GuidedTourView.swift", "source_location": "L162"}, {"caller_nid": "guidedtourview_guidedtourview_fullcard", "callee": "foregroundStyle", "source_file": "Ninety/View/Root/GuidedTourView.swift", "source_location": "L162"}, {"caller_nid": "guidedtourview_guidedtourview_fullcard", "callee": "font", "source_file": "Ninety/View/Root/GuidedTourView.swift", "source_location": "L162"}, {"caller_nid": "guidedtourview_guidedtourview_fullcard", "callee": "Text", "source_file": "Ninety/View/Root/GuidedTourView.swift", "source_location": "L162"}, {"caller_nid": "guidedtourview_guidedtourview_fullcard", "callee": "localized", "source_file": "Ninety/View/Root/GuidedTourView.swift", "source_location": "L162"}, {"caller_nid": "guidedtourview_guidedtourview_fullcard", "callee": "min", "source_file": "Ninety/View/Root/GuidedTourView.swift", "source_location": "L174"}, {"caller_nid": "guidedtourview_guidedtourview_fullcard", "callee": "RoundedRectangle", "source_file": "Ninety/View/Root/GuidedTourView.swift", "source_location": "L175"}, {"caller_nid": "guidedtourview_guidedtourview_fullcard", "callee": "Spacer", "source_file": "Ninety/View/Root/GuidedTourView.swift", "source_location": "L178"}, {"caller_nid": "guidedtourview_guidedtourview_spotcard", "callee": "frame", "source_file": "Ninety/View/Root/GuidedTourView.swift", "source_location": "L187"}, {"caller_nid": "guidedtourview_guidedtourview_spotcard", "callee": "offsetBy", "source_file": "Ninety/View/Root/GuidedTourView.swift", "source_location": "L188"}, {"caller_nid": "guidedtourview_guidedtourview_spotcard", "callee": "insetBy", "source_file": "Ninety/View/Root/GuidedTourView.swift", "source_location": "L190"}, {"caller_nid": "guidedtourview_guidedtourview_spotcard", "callee": "ignoresSafeArea", "source_file": "Ninety/View/Root/GuidedTourView.swift", "source_location": "L202"}, {"caller_nid": "guidedtourview_guidedtourview_spotcard", "callee": "ZStack", "source_file": "Ninety/View/Root/GuidedTourView.swift", "source_location": "L202"}, {"caller_nid": "guidedtourview_guidedtourview_spotcard", "callee": "ignoresSafeArea", "source_file": "Ninety/View/Root/GuidedTourView.swift", "source_location": "L204"}, {"caller_nid": "guidedtourview_guidedtourview_spotcard", "callee": "foregroundStyle", "source_file": "Ninety/View/Root/GuidedTourView.swift", "source_location": "L204"}, {"caller_nid": "guidedtourview_guidedtourview_spotcard", "callee": "fill", "source_file": "Ninety/View/Root/GuidedTourView.swift", "source_location": "L204"}, {"caller_nid": "guidedtourview_guidedtourview_spotcard", "callee": "FillStyle", "source_file": "Ninety/View/Root/GuidedTourView.swift", "source_location": "L205"}, {"caller_nid": "guidedtourview_guidedtourview_spotcard", "callee": "opacity", "source_file": "Ninety/View/Root/GuidedTourView.swift", "source_location": "L206"}, {"caller_nid": "guidedtourview_guidedtourview_spotcard", "callee": "position", "source_file": "Ninety/View/Root/GuidedTourView.swift", "source_location": "L210"}, {"caller_nid": "guidedtourview_guidedtourview_spotcard", "callee": "shadow", "source_file": "Ninety/View/Root/GuidedTourView.swift", "source_location": "L210"}, {"caller_nid": "guidedtourview_guidedtourview_spotcard", "callee": "frame", "source_file": "Ninety/View/Root/GuidedTourView.swift", "source_location": "L210"}, {"caller_nid": "guidedtourview_guidedtourview_spotcard", "callee": "strokeBorder", "source_file": "Ninety/View/Root/GuidedTourView.swift", "source_location": "L210"}, {"caller_nid": "guidedtourview_guidedtourview_spotcard", "callee": "RoundedRectangle", "source_file": "Ninety/View/Root/GuidedTourView.swift", "source_location": "L210"}, {"caller_nid": "guidedtourview_guidedtourview_spotcard", "callee": "opacity", "source_file": "Ninety/View/Root/GuidedTourView.swift", "source_location": "L213"}, {"caller_nid": "guidedtourview_guidedtourview_spotcard", "callee": "position", "source_file": "Ninety/View/Root/GuidedTourView.swift", "source_location": "L217"}, {"caller_nid": "guidedtourview_guidedtourview_spotcard", "callee": "scaleEffect", "source_file": "Ninety/View/Root/GuidedTourView.swift", "source_location": "L217"}, {"caller_nid": "guidedtourview_guidedtourview_spotcard", "callee": "glassEffect", "source_file": "Ninety/View/Root/GuidedTourView.swift", "source_location": "L217"}, {"caller_nid": "guidedtourview_guidedtourview_spotcard", "callee": "frame", "source_file": "Ninety/View/Root/GuidedTourView.swift", "source_location": "L217"}, {"caller_nid": "guidedtourview_guidedtourview_spotcard", "callee": "padding", "source_file": "Ninety/View/Root/GuidedTourView.swift", "source_location": "L217"}, {"caller_nid": "guidedtourview_guidedtourview_spotcard", "callee": "padding", "source_file": "Ninety/View/Root/GuidedTourView.swift", "source_location": "L217"}, {"caller_nid": "guidedtourview_guidedtourview_spotcard", "callee": "VStack", "source_file": "Ninety/View/Root/GuidedTourView.swift", "source_location": "L217"}, {"caller_nid": "guidedtourview_guidedtourview_spotcard", "callee": "HStack", "source_file": "Ninety/View/Root/GuidedTourView.swift", "source_location": "L218"}, {"caller_nid": "guidedtourview_guidedtourview_spotcard", "callee": "symbolRenderingMode", "source_file": "Ninety/View/Root/GuidedTourView.swift", "source_location": "L219"}, {"caller_nid": "guidedtourview_guidedtourview_spotcard", "callee": "foregroundStyle", "source_file": "Ninety/View/Root/GuidedTourView.swift", "source_location": "L219"}, {"caller_nid": "guidedtourview_guidedtourview_spotcard", "callee": "font", "source_file": "Ninety/View/Root/GuidedTourView.swift", "source_location": "L219"}, {"caller_nid": "guidedtourview_guidedtourview_spotcard", "callee": "Image", "source_file": "Ninety/View/Root/GuidedTourView.swift", "source_location": "L219"}, {"caller_nid": "guidedtourview_guidedtourview_spotcard", "callee": "font", "source_file": "Ninety/View/Root/GuidedTourView.swift", "source_location": "L223"}, {"caller_nid": "guidedtourview_guidedtourview_spotcard", "callee": "Text", "source_file": "Ninety/View/Root/GuidedTourView.swift", "source_location": "L223"}, {"caller_nid": "guidedtourview_guidedtourview_spotcard", "callee": "localized", "source_file": "Ninety/View/Root/GuidedTourView.swift", "source_location": "L223"}, {"caller_nid": "guidedtourview_guidedtourview_spotcard", "callee": "Spacer", "source_file": "Ninety/View/Root/GuidedTourView.swift", "source_location": "L225"}, {"caller_nid": "guidedtourview_guidedtourview_spotcard", "callee": "lineLimit", "source_file": "Ninety/View/Root/GuidedTourView.swift", "source_location": "L228"}, {"caller_nid": "guidedtourview_guidedtourview_spotcard", "callee": "lineSpacing", "source_file": "Ninety/View/Root/GuidedTourView.swift", "source_location": "L228"}, {"caller_nid": "guidedtourview_guidedtourview_spotcard", "callee": "foregroundStyle", "source_file": "Ninety/View/Root/GuidedTourView.swift", "source_location": "L228"}, {"caller_nid": "guidedtourview_guidedtourview_spotcard", "callee": "font", "source_file": "Ninety/View/Root/GuidedTourView.swift", "source_location": "L228"}, {"caller_nid": "guidedtourview_guidedtourview_spotcard", "callee": "Text", "source_file": "Ninety/View/Root/GuidedTourView.swift", "source_location": "L228"}, {"caller_nid": "guidedtourview_guidedtourview_spotcard", "callee": "localized", "source_file": "Ninety/View/Root/GuidedTourView.swift", "source_location": "L228"}, {"caller_nid": "guidedtourview_guidedtourview_spotcard", "callee": "padding", "source_file": "Ninety/View/Root/GuidedTourView.swift", "source_location": "L234"}, {"caller_nid": "guidedtourview_guidedtourview_spotcard", "callee": "min", "source_file": "Ninety/View/Root/GuidedTourView.swift", "source_location": "L238"}, {"caller_nid": "guidedtourview_guidedtourview_spotcard", "callee": "RoundedRectangle", "source_file": "Ninety/View/Root/GuidedTourView.swift", "source_location": "L239"}, {"caller_nid": "guidedtourview_guidedtourview_go", "callee": "impactOccurred", "source_file": "Ninety/View/Root/GuidedTourView.swift", "source_location": "L308"}, {"caller_nid": "guidedtourview_guidedtourview_go", "callee": "withAnimation", "source_file": "Ninety/View/Root/GuidedTourView.swift", "source_location": "L311"}, {"caller_nid": "guidedtourview_guidedtourview_go", "callee": "withAnimation", "source_file": "Ninety/View/Root/GuidedTourView.swift", "source_location": "L312"}, {"caller_nid": "guidedtourview_guidedtourview_go", "callee": "delay", "source_file": "Ninety/View/Root/GuidedTourView.swift", "source_location": "L312"}, {"caller_nid": "guidedtourview_guidedtourview_go", "callee": "withAnimation", "source_file": "Ninety/View/Root/GuidedTourView.swift", "source_location": "L315"}, {"caller_nid": "guidedtourview_guidedtourview_go", "callee": "delay", "source_file": "Ninety/View/Root/GuidedTourView.swift", "source_location": "L315"}, {"caller_nid": "guidedtourview_guidedtourview_close", "callee": "impactOccurred", "source_file": "Ninety/View/Root/GuidedTourView.swift", "source_location": "L319"}, {"caller_nid": "guidedtourview_guidedtourview_close", "callee": "withAnimation", "source_file": "Ninety/View/Root/GuidedTourView.swift", "source_location": "L320"}, {"caller_nid": "guidedtourview_guidedtourview_close", "callee": "asyncAfter", "source_file": "Ninety/View/Root/GuidedTourView.swift", "source_location": "L321"}, {"caller_nid": "guidedtourview_spotlightshape_path", "callee": "addRect", "source_file": "Ninety/View/Root/GuidedTourView.swift", "source_location": "L332"}, {"caller_nid": "guidedtourview_spotlightshape_path", "callee": "addPath", "source_file": "Ninety/View/Root/GuidedTourView.swift", "source_location": "L333"}, {"caller_nid": "guidedtourview_tourtargetmodifier_body", "callee": "onGeometryChange", "source_file": "Ninety/View/Root/GuidedTourView.swift", "source_location": "L347"}, {"caller_nid": "guidedtourview_tourtargetmodifier_body", "callee": "frame", "source_file": "Ninety/View/Root/GuidedTourView.swift", "source_location": "L349"}, {"caller_nid": "guidedtourview_view_tourtarget", "callee": "modifier", "source_file": "Ninety/View/Root/GuidedTourView.swift", "source_location": "L362"}, {"caller_nid": "guidedtourview_comparable_clamped", "callee": "min", "source_file": "Ninety/View/Root/GuidedTourView.swift", "source_location": "L369"}, {"caller_nid": "guidedtourview_comparable_clamped", "callee": "max", "source_file": "Ninety/View/Root/GuidedTourView.swift", "source_location": "L369"}]}